{
  "predictions": [
    {
      "x": 399,
      "y": 254,
      "width": 793,
      "height": 242,
      "confidence": 0.8158513903617859,
      "class": "pothole",
      "class_id": 2,
      "detection_id": "0009b13c-af9e-4e1d-b3c0-9aa989d7b4e1",
      "image_path": "data/train_images/p1567.jpg",
      "prediction_type": "ObjectDetectionModel"
    },
    {
      "x": 93,
      "y": 268,
      "width": 187,
      "height": 49,
      "confidence": 0.7304272651672363,
      "class": "L2",
      "class_id": 1,
      "detection_id": "e9207dcf-ff8b-4c44-876c-faed8128a23c",
      "image_path": "data/train_images/p1567.jpg",
      "prediction_type": "ObjectDetectionModel"
    },
    {
      "x": 482,
      "y": 260,
      "width": 654,
      "height": 52,
      "confidence": 0.6116636991500854,
      "class": "L1",
      "class_id": 0,
      "detection_id": "6c9e366d-84db-4a9c-b7cc-b6a6e61a21c5",
      "image_path": "data/train_images/p1567.jpg",
      "prediction_type": "ObjectDetectionModel"
    }
  ],
  "image": {
    "width": "824",
    "height": "512"
  }
}