{
  "predictions": [
    {
      "x": 165.0,
      "y": 138.5,
      "width": 184.0,
      "height": 99.0,
      "confidence": 0.9174476265907288,
      "class": "pothole",
      "class_id": 2,
      "detection_id": "08393840-6680-45af-81d1-1171355cf56a",
      "image_path": "data/train_images/p240.jpg",
      "prediction_type": "ObjectDetectionModel"
    },
    {
      "x": 204.5,
      "y": 124.0,
      "width": 173.0,
      "height": 12.0,
      "confidence": 0.7098181247711182,
      "class": "L1",
      "class_id": 0,
      "detection_id": "dcfa421f-0aa2-4876-b236-ce2b3ecca298",
      "image_path": "data/train_images/p240.jpg",
      "prediction_type": "ObjectDetectionModel"
    },
    {
      "x": 62.5,
      "y": 123.0,
      "width": 125.0,
      "height": 12.0,
      "confidence": 0.5829411745071411,
      "class": "L2",
      "class_id": 1,
      "detection_id": "57143917-8df5-4d31-b2fe-811722d545fa",
      "image_path": "data/train_images/p240.jpg",
      "prediction_type": "ObjectDetectionModel"
    }
  ],
  "image": {
    "width": "336",
    "height": "281"
  }
}