[
  {
    "name": "pothole",
    "class": 2,
    "box": {
      "x1": 72.0,
      "y1": 1.0,
      "x2": 267.0,
      "y2": 307.0
    },
    "segments": {
      "x": [
        267,
        267,
        212,
        205,
        199,
        193,
        166,
        152,
        122,
        96,
        87,
        72,
        72,
        84,
        143
      ],
      "y": [
        1,
        15,
        266,
        285,
        295,
        301,
        307,
        307,
        281,
        255,
        242,
        215,
        120,
        96,
        1
      ]
    }
  },
  {
    "name": "L2",
    "class": 1,
    "box": {
      "x1": 148.0,
      "y1": 1.0,
      "x2": 177.0,
      "y2": 69.0
    },
    "segments": {
      "x": [
        172,
        177,
        177,
        174,
        148,
        148
      ],
      "y": [
        1,
        44,
        63,
        69,
        69,
        1
      ]
    }
  },
  {
    "name": "L1",
    "class": 0,
    "box": {
      "x1": 152.0,
      "y1": 64.0,
      "x2": 192.0,
      "y2": 336.0
    },
    "segments": {
      "x": [
        153,
        174,
        176,
        189,
        192,
        191,
        169,
        168,
        152,
        152
      ],
      "y": [
        64,
        66,
        72,
        261,
        335,
        336,
        336,
        333,
        116,
        65
      ]
    }
  }
]