[
  {
    "name": "L2",
    "class": 1,
    "box": {
      "x1": 1.0,
      "y1": 242.0,
      "x2": 135.0,
      "y2": 314.0
    },
    "segments": {
      "x": [
        135,
        135,
        5,
        1,
        1,
        120
      ],
      "y": [
        242,
        259,
        314,
        314,
        291,
        242
      ]
    }
  },
  {
    "name": "L1",
    "class": 0,
    "box": {
      "x1": 105.0,
      "y1": 160.0,
      "x2": 347.0,
      "y2": 267.0
    },
    "segments": {
      "x": [
        346,
        347,
        346,
        342,
        332,
        114,
        105,
        105,
        158,
        294,
        338,
        343
      ],
      "y": [
        165,
        168,
        171,
        174,
        179,
        267,
        267,
        251,
        227,
        175,
        160,
        161
      ]
    }
  },
  {
    "name": "pothole",
    "class": 2,
    "box": {
      "x1": 131.0,
      "y1": 176.0,
      "x2": 286.0,
      "y2": 267.0
    },
    "segments": {
      "x": [
        131,
        131,
        210,
        282,
        286,
        286,
        280,
        278,
        160
      ],
      "y": [
        267,
        208,
        176,
        176,
        198,
        209,
        237,
        239,
        267
      ]
    }
  }
]