[
  {
    "name": "L1",
    "class": 0,
    "box": {
      "x1": 45.0,
      "y1": 41.0,
      "x2": 325.0,
      "y2": 293.0
    },
    "segments": {
      "x": [
        45,
        48,
        62,
        88,
        319,
        324,
        325,
        324,
        322,
        313,
        305,
        50,
        45
      ],
      "y": [
        41,
        41,
        50,
        70,
        258,
        263,
        266,
        291,
        293,
        293,
        288,
        75,
        70
      ]
    }
  },
  {
    "name": "pothole",
    "class": 1,
    "box": {
      "x1": 116.0,
      "y1": 76.0,
      "x2": 282.0,
      "y2": 310.0
    },
    "segments": {
      "x": [
        186,
        138,
        129,
        117,
        116,
        161,
        164,
        269,
        277,
        281,
        282,
        282,
        281
      ],
      "y": [
        310,
        310,
        297,
        230,
        76,
        76,
        77,
        155,
        163,
        170,
        174,
        219,
        223
      ]
    }
  }
]