[
  {
    "name": "L1",
    "class": 0,
    "box": {
      "x1": 208.0,
      "y1": 35.0,
      "x2": 238.0,
      "y2": 316.0
    },
    "segments": {
      "x": [
        236,
        238,
        238,
        230,
        228,
        209,
        208,
        208,
        217,
        220
      ],
      "y": [
        35,
        37,
        95,
        314,
        316,
        316,
        315,
        257,
        37,
        35
      ]
    }
  },
  {
    "name": "pothole",
    "class": 1,
    "box": {
      "x1": 142.0,
      "y1": 114.0,
      "x2": 272.0,
      "y2": 291.0
    },
    "segments": {
      "x": [
        248,
        238,
        204,
        188,
        162,
        152,
        142,
        142,
        147,
        213,
        253,
        257,
        258,
        272,
        272,
        267,
        252
      ],
      "y": [
        288,
        291,
        290,
        284,
        254,
        235,
        212,
        170,
        165,
        115,
        114,
        115,
        116,
        188,
        248,
        259,
        284
      ]
    }
  }
]