[
  {
    "name": "L1",
    "class": 0,
    "box": {
      "x1": 206.0,
      "y1": 19.0,
      "x2": 231.0,
      "y2": 223.0
    },
    "segments": {
      "x": [
        206,
        215,
        216,
        219,
        231,
        231,
        230,
        220,
        219,
        217,
        210,
        206
      ],
      "y": [
        19,
        19,
        20,
        46,
        204,
        220,
        222,
        223,
        222,
        217,
        131,
        69
      ]
    }
  },
  {
    "name": "pothole",
    "class": 1,
    "box": {
      "x1": 119.0,
      "y1": 57.0,
      "x2": 261.0,
      "y2": 377.0
    },
    "segments": {
      "x": [
        199,
        223,
        235,
        241,
        244,
        258,
        261,
        261,
        259,
        119,
        119,
        140,
        142
      ],
      "y": [
        57,
        64,
        73,
        81,
        89,
        226,
        318,
        372,
        377,
        377,
        193,
        58,
        57
      ]
    }
  }
]