[
  {
    "name": "L2",
    "class": 1,
    "box": {
      "x1": 190.0,
      "y1": 164.0,
      "x2": 225.0,
      "y2": 377.0
    },
    "segments": {
      "x": [
        190,
        199,
        200,
        225,
        225,
        211,
        190
      ],
      "y": [
        165,
        164,
        169,
        370,
        377,
        377,
        193
      ]
    }
  },
  {
    "name": "L1",
    "class": 0,
    "box": {
      "x1": 181.0,
      "y1": 67.0,
      "x2": 198.0,
      "y2": 166.0
    },
    "segments": {
      "x": [
        181,
        187,
        189,
        192,
        196,
        198,
        198,
        197,
        190,
        181
      ],
      "y": [
        67,
        67,
        78,
        99,
        133,
        156,
        163,
        166,
        166,
        96
      ]
    }
  },
  {
    "name": "pothole",
    "class": 2,
    "box": {
      "x1": 96.0,
      "y1": 38.0,
      "x2": 357.0,
      "y2": 377.0
    },
    "segments": {
      "x": [
        96,
        208,
        284,
        298,
        313,
        317,
        352,
        357,
        321,
        139,
        135,
        122,
        114,
        96
      ],
      "y": [
        38,
        39,
        48,
        55,
        70,
        77,
        225,
        358,
        377,
        377,
        372,
        340,
        300,
        114
      ]
    }
  }
]