[
  {
    "name": "pothole",
    "class": 1,
    "box": {
      "x1": 166.0,
      "y1": 41.0,
      "x2": 383.0,
      "y2": 274.0
    },
    "segments": {
      "x": [
        318,
        357,
        367,
        383,
        383,
        372,
        361,
        353,
        340,
        333,
        315,
        300,
        258,
        230,
        221,
        198,
        188,
        170,
        168,
        166,
        166,
        169,
        183,
        202,
        232,
        264,
        316
      ],
      "y": [
        42,
        80,
        92,
        125,
        137,
        177,
        209,
        227,
        246,
        253,
        266,
        272,
        274,
        274,
        272,
        264,
        254,
        220,
        214,
        188,
        123,
        96,
        79,
        64,
        48,
        41,
        41
      ]
    }
  },
  {
    "name": "L1",
    "class": 0,
    "box": {
      "x1": 261.0,
      "y1": 105.0,
      "x2": 278.0,
      "y2": 299.0
    },
    "segments": {
      "x": [
        274,
        276,
        277,
        278,
        276,
        272,
        265,
        262,
        261,
        261
      ],
      "y": [
        105,
        108,
        118,
        294,
        297,
        299,
        299,
        296,
        294,
        105
      ]
    }
  }
]