[
  {
    "name": "L1",
    "class": 0,
    "box": {
      "x1": 123.0,
      "y1": 85.0,
      "x2": 363.0,
      "y2": 294.0
    },
    "segments": {
      "x": [
        362,
        363,
        363,
        359,
        144,
        134,
        131,
        123,
        123,
        133,
        235,
        340,
        350,
        359
      ],
      "y": [
        87,
        89,
        96,
        101,
        288,
        294,
        294,
        283,
        278,
        268,
        179,
        90,
        85,
        85
      ]
    }
  },
  {
    "name": "pothole",
    "class": 1,
    "box": {
      "x1": 0.0,
      "y1": 91.0,
      "x2": 347.0,
      "y2": 377.0
    },
    "segments": {
      "x": [
        328,
        347,
        336,
        323,
        275,
        266,
        213,
        153,
        2,
        0,
        0,
        2,
        4
      ],
      "y": [
        91,
        171,
        210,
        239,
        309,
        319,
        358,
        377,
        377,
        372,
        102,
        93,
        91
      ]
    }
  }
]