[
  {
    "name": "pothole",
    "class": 1,
    "box": {
      "x1": 22.0,
      "y1": 25.0,
      "x2": 576.0,
      "y2": 542.0
    },
    "segments": {
      "x": [
        533,
        548,
        575,
        576,
        572,
        568,
        541,
        454,
        69,
        22,
        23,
        449,
        457,
        524
      ],
      "y": [
        27,
        122,
        376,
        417,
        516,
        526,
        537,
        542,
        541,
        538,
        515,
        32,
        26,
        25
      ]
    }
  },
  {
    "name": "L1",
    "class": 0,
    "box": {
      "x1": 475.0,
      "y1": 35.0,
      "x2": 497.0,
      "y2": 220.0
    },
    "segments": {
      "x": [
        493,
        496,
        497,
        495,
        493,
        476,
        475,
        475,
        476
      ],
      "y": [
        35,
        36,
        61,
        217,
        220,
        220,
        218,
        36,
        35
      ]
    }
  }
]