[
  {
    "name": "L1",
    "class": 0,
    "box": {
      "x1": 252.0,
      "y1": 275.0,
      "x2": 823.0,
      "y2": 415.0
    },
    "segments": {
      "x": [
        823,
        823,
        270,
        258,
        254,
        252,
        252,
        258,
        794
      ],
      "y": [
        275,
        315,
        415,
        415,
        413,
        399,
        372,
        369,
        275
      ]
    }
  },
  {
    "name": "pothole",
    "class": 1,
    "box": {
      "x1": 46.0,
      "y1": 170.0,
      "x2": 751.0,
      "y2": 582.0
    },
    "segments": {
      "x": [
        750,
        751,
        741,
        679,
        654,
        619,
        581,
        229,
        136,
        114,
        50,
        46,
        49,
        162,
        220,
        645,
        672,
        684
      ],
      "y": [
        273,
        337,
        364,
        487,
        514,
        539,
        549,
        580,
        582,
        574,
        510,
        443,
        348,
        218,
        173,
        170,
        173,
        183
      ]
    }
  }
]