[
  {
    "name": "pothole",
    "class": 1,
    "box": {
      "x1": 226.0,
      "y1": 68.0,
      "x2": 659.0,
      "y2": 441.0
    },
    "segments": {
      "x": [
        226,
        346,
        358,
        370,
        443,
        640,
        655,
        659,
        603,
        597,
        472,
        455,
        421,
        413,
        396,
        358,
        226
      ],
      "y": [
        219,
        80,
        72,
        68,
        77,
        237,
        256,
        269,
        381,
        387,
        436,
        440,
        441,
        440,
        429,
        389,
        233
      ]
    }
  },
  {
    "name": "L1",
    "class": 0,
    "box": {
      "x1": 378.0,
      "y1": 19.0,
      "x2": 468.0,
      "y2": 387.0
    },
    "segments": {
      "x": [
        380,
        431,
        434,
        468,
        468,
        467,
        409,
        406,
        400,
        395,
        378,
        378
      ],
      "y": [
        19,
        19,
        21,
        357,
        386,
        387,
        387,
        378,
        338,
        288,
        82,
        21
      ]
    }
  }
]