[
  {
    "name": "pothole",
    "class": 2,
    "box": {
      "x1": 156.0,
      "y1": 134.0,
      "x2": 967.0,
      "y2": 536.0
    },
    "segments": {
      "x": [
        967,
        907,
        669,
        653,
        553,
        306,
        261,
        231,
        219,
        156,
        156,
        299,
        312,
        396,
        506,
        727,
        844,
        880,
        936,
        967
      ],
      "y": [
        388,
        421,
        533,
        536,
        534,
        522,
        509,
        492,
        482,
        409,
        321,
        194,
        187,
        161,
        134,
        134,
        165,
        187,
        234,
        289
      ]
    }
  },
  {
    "name": "L1",
    "class": 0,
    "box": {
      "x1": 522.0,
      "y1": 285.0,
      "x2": 1159.0,
      "y2": 358.0
    },
    "segments": {
      "x": [
        1159,
        1159,
        1150,
        930,
        736,
        604,
        526,
        522,
        522,
        530,
        1053
      ],
      "y": [
        285,
        317,
        320,
        339,
        353,
        358,
        358,
        347,
        328,
        324,
        285
      ]
    }
  },
  {
    "name": "L2",
    "class": 1,
    "box": {
      "x1": 0.0,
      "y1": 326.0,
      "x2": 523.0,
      "y2": 392.0
    },
    "segments": {
      "x": [
        521,
        523,
        515,
        499,
        340,
        13,
        0,
        0,
        11,
        357
      ],
      "y": [
        326,
        352,
        358,
        361,
        373,
        392,
        390,
        354,
        350,
        326
      ]
    }
  }
]