[
  {
    "name": "pothole",
    "class": 2,
    "box": {
      "x1": 327.0,
      "y1": 109.0,
      "x2": 605.0,
      "y2": 439.0
    },
    "segments": {
      "x": [
        483,
        475,
        428,
        408,
        394,
        373,
        357,
        327,
        327,
        409,
        440,
        481,
        490,
        548,
        605,
        605,
        569,
        552
      ],
      "y": [
        439,
        439,
        425,
        417,
        409,
        393,
        377,
        341,
        295,
        109,
        109,
        115,
        124,
        226,
        348,
        366,
        399,
        409
      ]
    }
  },
  {
    "name": "L2",
    "class": 1,
    "box": {
      "x1": 442.0,
      "y1": 8.0,
      "x2": 479.0,
      "y2": 199.0
    },
    "segments": {
      "x": [
        479,
        479,
        470,
        468,
        442,
        442
      ],
      "y": [
        8,
        43,
        191,
        199,
        199,
        8
      ]
    }
  },
  {
    "name": "L1",
    "class": 0,
    "box": {
      "x1": 442.0,
      "y1": 196.0,
      "x2": 474.0,
      "y2": 514.0
    },
    "segments": {
      "x": [
        442,
        474,
        474,
        442
      ],
      "y": [
        196,
        198,
        514,
        514
      ]
    }
  }
]