[
  {
    "name": "pothole",
    "class": 1,
    "box": {
      "x1": 26.0,
      "y1": 42.0,
      "x2": 559.0,
      "y2": 424.0
    },
    "segments": {
      "x": [
        544,
        550,
        559,
        557,
        543,
        523,
        478,
        377,
        370,
        328,
        137,
        48,
        26,
        26,
        203,
        320,
        346,
        355,
        422,
        489,
        527
      ],
      "y": [
        102,
        124,
        241,
        261,
        291,
        317,
        360,
        420,
        422,
        424,
        424,
        418,
        410,
        406,
        182,
        61,
        46,
        44,
        42,
        65,
        87
      ]
    }
  },
  {
    "name": "L1",
    "class": 0,
    "box": {
      "x1": 361.0,
      "y1": 18.0,
      "x2": 406.0,
      "y2": 316.0
    },
    "segments": {
      "x": [
        403,
        406,
        406,
        391,
        390,
        388,
        386,
        362,
        361,
        361,
        367,
        378,
        379,
        381
      ],
      "y": [
        18,
        19,
        29,
        307,
        312,
        315,
        316,
        315,
        312,
        235,
        147,
        24,
        19,
        18
      ]
    }
  }
]