[
  {
    "name": "L2",
    "class": 1,
    "box": {
      "x1": 132.0,
      "y1": 16.0,
      "x2": 205.0,
      "y2": 149.0
    },
    "segments": {
      "x": [
        132,
        140,
        174,
        205,
        205,
        203,
        195,
        192,
        132
      ],
      "y": [
        16,
        16,
        77,
        138,
        144,
        146,
        149,
        147,
        26
      ]
    }
  },
  {
    "name": "L1",
    "class": 0,
    "box": {
      "x1": 193.0,
      "y1": 144.0,
      "x2": 270.0,
      "y2": 266.0
    },
    "segments": {
      "x": [
        195,
        197,
        205,
        207,
        215,
        267,
        270,
        270,
        266,
        258,
        253,
        251,
        193
      ],
      "y": [
        147,
        146,
        144,
        145,
        157,
        254,
        261,
        264,
        266,
        266,
        264,
        261,
        150
      ]
    }
  },
  {
    "name": "pothole",
    "class": 2,
    "box": {
      "x1": 99.0,
      "y1": 84.0,
      "x2": 302.0,
      "y2": 242.0
    },
    "segments": {
      "x": [
        302,
        294,
        282,
        252,
        233,
        206,
        159,
        148,
        99,
        99,
        123,
        127,
        159,
        181,
        215,
        257,
        264,
        278,
        282,
        294,
        302
      ],
      "y": [
        177,
        189,
        200,
        221,
        233,
        242,
        242,
        233,
        177,
        134,
        107,
        104,
        88,
        84,
        84,
        102,
        107,
        120,
        125,
        145,
        161
      ]
    }
  }
]