[
  {
    "name": "pothole",
    "class": 2,
    "box": {
      "x1": 164.0,
      "y1": 156.0,
      "x2": 466.0,
      "y2": 314.0
    },
    "segments": {
      "x": [
        466,
        466,
        405,
        396,
        365,
        333,
        301,
        238,
        204,
        191,
        180,
        167,
        165,
        164,
        166,
        172,
        218,
        266,
        407,
        458
      ],
      "y": [
        203,
        210,
        282,
        288,
        304,
        313,
        314,
        301,
        289,
        282,
        271,
        252,
        247,
        205,
        200,
        196,
        173,
        156,
        156,
        191
      ]
    }
  },
  {
    "name": "L2",
    "class": 1,
    "box": {
      "x1": 2.0,
      "y1": 211.0,
      "x2": 120.0,
      "y2": 241.0
    },
    "segments": {
      "x": [
        120,
        120,
        2,
        2
      ],
      "y": [
        211,
        241,
        241,
        211
      ]
    }
  },
  {
    "name": "L1",
    "class": 0,
    "box": {
      "x1": 116.0,
      "y1": 211.0,
      "x2": 618.0,
      "y2": 244.0
    },
    "segments": {
      "x": [
        618,
        618,
        495,
        265,
        129,
        116,
        116
      ],
      "y": [
        211,
        242,
        244,
        244,
        240,
        238,
        211
      ]
    }
  }
]