[
  {
    "name": "pothole",
    "class": 1,
    "box": {
      "x1": 77.0,
      "y1": 125.0,
      "x2": 589.0,
      "y2": 349.0
    },
    "segments": {
      "x": [
        589,
        587,
        585,
        551,
        531,
        433,
        393,
        80,
        77,
        78,
        108,
        113,
        375,
        419,
        424,
        582,
        586
      ],
      "y": [
        245,
        278,
        283,
        308,
        320,
        349,
        349,
        310,
        297,
        268,
        219,
        214,
        125,
        125,
        127,
        234,
        238
      ]
    }
  },
  {
    "name": "L1",
    "class": 0,
    "box": {
      "x1": 127.0,
      "y1": 253.0,
      "x2": 645.0,
      "y2": 273.0
    },
    "segments": {
      "x": [
        127,
        127,
        129,
        132,
        645,
        645,
        643,
        134
      ],
      "y": [
        270,
        257,
        254,
        253,
        254,
        268,
        270,
        273
      ]
    }
  }
]