[
  {
    "name": "pothole",
    "class": 1,
    "box": {
      "x1": 339.0,
      "y1": 251.0,
      "x2": 579.0,
      "y2": 596.0
    },
    "segments": {
      "x": [
        397,
        420,
        469,
        499,
        552,
        565,
        574,
        579,
        579,
        577,
        571,
        565,
        552,
        502,
        491,
        475,
        405,
        395,
        384,
        349,
        340,
        339,
        340,
        343,
        355
      ],
      "y": [
        252,
        251,
        252,
        279,
        339,
        362,
        392,
        425,
        457,
        476,
        494,
        506,
        525,
        579,
        588,
        596,
        595,
        588,
        576,
        525,
        504,
        278,
        274,
        271,
        265
      ]
    }
  },
  {
    "name": "L1",
    "class": 0,
    "box": {
      "x1": 436.0,
      "y1": 137.0,
      "x2": 469.0,
      "y2": 533.0
    },
    "segments": {
      "x": [
        457,
        459,
        462,
        469,
        467,
        463,
        445,
        442,
        438,
        436,
        436,
        438
      ],
      "y": [
        137,
        139,
        203,
        509,
        525,
        533,
        533,
        529,
        466,
        402,
        139,
        137
      ]
    }
  }
]