[
  {
    "name": "pothole",
    "class": 2,
    "box": {
      "x1": 342.0,
      "y1": 141.0,
      "x2": 601.0,
      "y2": 599.0
    },
    "segments": {
      "x": [
        491,
        449,
        394,
        368,
        342,
        342,
        371,
        387,
        397,
        403,
        455,
        501,
        559,
        601,
        601,
        582
      ],
      "y": [
        599,
        599,
        537,
        495,
        446,
        327,
        221,
        174,
        152,
        148,
        141,
        141,
        226,
        314,
        429,
        472
      ]
    }
  },
  {
    "name": "L2",
    "class": 1,
    "box": {
      "x1": 412.0,
      "y1": 3.0,
      "x2": 462.0,
      "y2": 191.0
    },
    "segments": {
      "x": [
        462,
        462,
        457,
        452,
        412,
        412
      ],
      "y": [
        3,
        65,
        174,
        191,
        191,
        3
      ]
    }
  },
  {
    "name": "L1",
    "class": 0,
    "box": {
      "x1": 406.0,
      "y1": 184.0,
      "x2": 457.0,
      "y2": 639.0
    },
    "segments": {
      "x": [
        456,
        457,
        445,
        406,
        406
      ],
      "y": [
        185,
        260,
        639,
        639,
        184
      ]
    }
  }
]