[
  {
    "name": "L2",
    "class": 1,
    "box": {
      "x1": 19.0,
      "y1": 30.0,
      "x2": 161.0,
      "y2": 196.0
    },
    "segments": {
      "x": [
        22,
        30,
        44,
        148,
        158,
        161,
        161,
        157,
        153,
        150,
        138,
        19,
        19
      ],
      "y": [
        30,
        30,
        45,
        169,
        182,
        189,
        192,
        196,
        196,
        194,
        182,
        41,
        34
      ]
    }
  },
  {
    "name": "L1",
    "class": 0,
    "box": {
      "x1": 154.0,
      "y1": 192.0,
      "x2": 285.0,
      "y2": 347.0
    },
    "segments": {
      "x": [
        160,
        164,
        166,
        171,
        285,
        285,
        282,
        278,
        275,
        271,
        225,
        162,
        154,
        154
      ],
      "y": [
        194,
        192,
        192,
        196,
        334,
        342,
        345,
        347,
        347,
        345,
        291,
        214,
        201,
        200
      ]
    }
  },
  {
    "name": "pothole",
    "class": 2,
    "box": {
      "x1": 135.0,
      "y1": 167.0,
      "x2": 283.0,
      "y2": 305.0
    },
    "segments": {
      "x": [
        283,
        281,
        279,
        262,
        228,
        212,
        206,
        200,
        185,
        135,
        135,
        202,
        220,
        276,
        283
      ],
      "y": [
        279,
        283,
        285,
        297,
        303,
        305,
        305,
        304,
        297,
        247,
        214,
        167,
        167,
        262,
        275
      ]
    }
  }
]