[
  {
    "name": "L1",
    "class": 0,
    "box": {
      "x1": 284.0,
      "y1": 36.0,
      "x2": 307.0,
      "y2": 183.0
    },
    "segments": {
      "x": [
        298,
        299,
        300,
        307,
        307,
        306,
        288,
        285,
        284,
        284,
        285
      ],
      "y": [
        36,
        37,
        44,
        164,
        176,
        183,
        183,
        180,
        176,
        37,
        36
      ]
    }
  },
  {
    "name": "L1",
    "class": 0,
    "box": {
      "x1": 288.0,
      "y1": 162.0,
      "x2": 316.0,
      "y2": 427.0
    },
    "segments": {
      "x": [
        306,
        307,
        316,
        313,
        295,
        294,
        292,
        289,
        288,
        288,
        289
      ],
      "y": [
        162,
        164,
        425,
        427,
        427,
        426,
        416,
        372,
        307,
        163,
        162
      ]
    }
  },
  {
    "name": "pothole",
    "class": 1,
    "box": {
      "x1": 7.0,
      "y1": 17.0,
      "x2": 547.0,
      "y2": 442.0
    },
    "segments": {
      "x": [
        547,
        511,
        488,
        194,
        16,
        9,
        7,
        11,
        15,
        104,
        323,
        365,
        547
      ],
      "y": [
        331,
        361,
        376,
        442,
        442,
        428,
        394,
        79,
        56,
        38,
        17,
        18,
        115
      ]
    }
  }
]